<?xml version="1.0"?>
<ds:Signature xmlns:ds="http://www.w3.org/2000/09/xmldsig#" id="refQualifyingProperties">
  <ds:SignedInfo>
    <ds:CanonicalizationMethod Algorithm="http://www.w3.org/TR/2001/REC-xml-c14n-20010315"/>
    <ds:SignatureMethod Algorithm="http://www.w3.org/2000/09/xmldsig#sha1"/>
    <ds:Reference URI="#Salgraf-SignedProperties">
      <ds:DigestMethod Algorithm="http://www.w3.org/2000/09/xmldsig#sha1"/>
      <ds:DigestValue>9W0rNbAaoDX9cW8yS2p0RXh0b2w=</ds:DigestValue>
    </ds:Reference>
    <ds:Reference URI="#keyInfo">
      <ds:DigestMethod Algorithm="http://www.w3.org/2000/09/xmldsig#sha1"/>
      <ds:DigestValue>oVLaXEwgznOFqvzVXzYcSBdjXtU=</ds:DigestValue>
    </ds:Reference>
  </ds:SignedInfo>
  <ds:SignatureValue>MIIEvAIBADANBgkqhkiG9w0BAQEFAASCBKYwggSiAgEAAoIBAQCSk+QyNX8XsYiT&#xD;
KBAZURtDJOzAjQEkanb/h45vdwTcBS8VUgZsd9L2kwFsLwXcEM91CWFVgMmjzyod&#xD;
JKybCpdZpDfeePl7AjAqd4BY/VjzZSbmTjIugKj+p5EI0qG0xbHIFR9N3oKDmwOk&#xD;
zs1pskDg4/8bE+Mt9JsmlXjQwBwCSuBjxzAa/Y10OzNr1uhGpjAXC2tFxS1G754A&#xD;
zzwjYQz14hi+p6kleR3w5ClhcZRUuDiTpfFTHnQ3Q3Vn5AzDQ/FeSk0jgr1a4NpK&#xD;
+m52LSwBzoZykKmHszAkz+21Sn5/X04IJBT1T6aPhFqfP7xLp5cQrjmLmEWD0tNk&#xD;
7yIXcdRxAgMBAAECggEACzEXn23OQnTfxLyuXgB/YGUVXq5lg+5NH72t9nzT9ii/&#xD;
K5WTv/x2MzWOSkBc5iyyanFI6UpoGwXaZVdDhqMMY1/SlD4QboAARX3SYvkVLaBv&#xD;
k+4sjrhsLuWEgXPzvOXLaUeTmFKBDKNtZ8wSixt9MK63781Y701Z+1w2WVoRyWro&#xD;
miNvFv3hqxkIcV8Qq8KApsqkgo+TqI6jGmRoEE1vl3WX/XXhXl4npFgIUG52rmj5&#xD;
wmcv91iVBwJG4LkNOvXwQyEr9GdhM2Q88fxX2KebYigI4L3gUKmWrgBVIHPQ4SQK&#xD;
OIpj+IeHmj2YiE61tXN6dySysaxvGwsjFNDuiB7vcQKBgQDDFNKwOBMucrt7pguF&#xD;
GHBxkN74H7/qE6z4A/m94FkvunpDknWklhJ0q78rhWiXWPHx8HKU00wdzSEehPZw&#xD;
NgEixQwBJb9JnIwS7PVL8WDe0YUeGI4NiR+gvEuTBagBRX+u6GHe1BCw4kbWSEWI&#xD;
OKNLgsAiqRA1ugx2P1lIHrhhMwKBgQDAWZglUCQ/2d2rXxecvlDwmANah9UPNzxS&#xD;
cYBxicIWsGWcIKPbAZzJeYxMnulQopIVwt7uEhvIavz/wzaRF27X9Q07IWd9A9V6&#xD;
T2zKrcDXBfTxNqv+f88km+5mg8tZKUA+GMUM2T1Q2pu2YNayvGUXpbXs0CipSske&#xD;
vDJue9I7ywKBgBK4X9N7PhP5/JXMBFT8WGX9gfgLi+4Zf0K5lvCqo8RZv7vWRSXL&#xD;
JPA/PvQdNEE5ztXpvgUcFbTSZ3g3SDLSa997S0Cc77NPq31xccSc4C/hqUWPE6qm&#xD;
2vsgtpvgMhQVKECPmjy42vUucZ/Eha+hx8HKRUfOM3kEZoe+YoHyOL1TAoGARauu&#xD;
GkXO+3m0evA0o0ekFaFaBZ6Ro7NEHDCUb4uQS5uVEloYP6lz2t413ULqC5T3CP7O&#xD;
tLjGa2+lOBbDWwZ71akjI7nTvEp5NpYyN6972+aCdCRzY/lzVDVOwr8WFrOEW3mp&#xD;
ViARv4mPQR4OZisrCsew/5feQoOeGY3dTnt3CMUCgYBD4y17oF+9p3/gc87iTwcT&#xD;
ickDrLnNcswQ9hh58sDixhhS8rDz05cAZCBd9P3QPjDGXxrlQy7tCkyFC19zPVLI&#xD;
zzgURi9p5KJchf51nHi2cRBQtuSk37UUUjJCZazcYXvAkfT6pUneIkI2ancw/6DH&#xD;
W+sEfzO5mLhdMVnl6auXAw==</ds:SignatureValue>
<ds:Keyinfo id="keyInfo">
  <ds:X509Data>
    <ds:X509Certificate>10:cd:69:53:07:ba:02:57:86:9e:2a:4b:4b:2f:48:6a:dc:e3:&#xD;
         04:47:51:3e:88:a8:05:ec:11:3b:5e:66:7b:84:0e:9c:e1:ed:&#xD;
         ca:11:6a:42:ce:4d:17:99:d4:9e:6b:3b:62:a4:00:ab:32:2b:&#xD;
         49:23:fe:4f:ba:67:a1:ed:fa:75:8a:a2:92:d1:5b:97:01:70:&#xD;
         b3:bc:e6:7a:d1:24:cc:67:fb:66:48:fc:cc:8d:9f:27:08:6a:&#xD;
         e0:3b:22:6b:93:23:26:9f:6a:b4:85:2f:46:de:20:40:61:24:&#xD;
         4d:5b:fe:1a:80:80:16:96:3b:8e:af:77:81:1e:f3:bf:9b:2b:&#xD;
         6b:66:93:2c:51:e9:05:f2:b9:39:a5:cb:30:3f:c7:f8:8c:3a:&#xD;
         21:5a:dc:81:ca:4a:46:f4:ac:e9:41:29:5d:f8:f9:b9:7f:dc:&#xD;
         03:39:99:9d:29:ae:9e:44:73:48:02:de:46:c8:b4:8a:64:0c:&#xD;
         c4:ec:56:1b:90:c7:53:cb:c9:50:f6:9d:e9:0d:d9:42:f5:3d:&#xD;
         0f:41:a3:9f:62:d0:08:0f:2a:dd:36:e4:a0:38:c9:62:49:85:&#xD;
         c5:af:73:58:19:06:29:ed:e7:bf:a4:0c:cf:00:5c:36:49:fb:&#xD;
         42:6b:09:db:b0:cb:a4:f7:b5:1a:b8:59:54:e9:78:3b:32:3f:&#xD;
         b4:fd:a4:d1:35:3c:4d:3a:e6:24:87:69:fd:0b:9f:ba:62:ca:&#xD;
         38:5c:65:cf:df:a9:13:83:57:b0:f8:c5:03:ed:23:e2:f6:98:&#xD;
         64:ed:23:a8:0d:12:a6:e9:0e:a8:2d:76:21:f4:4a:d6:26:b7:&#xD;
         ea:e2:ac:a9:e2:7b:a9:98:2e:9d:38:22:d2:01:1a:19:72:f9:&#xD;
         df:db:20:5d:fc:fa:3f:1e:e5:d0:ef:68:e2:11:b2:25:f0:f1:&#xD;
         40:8a:de:39:9c:dd:b2:c3:78:82:7a:01:6b:85:6d:41:ce:00:&#xD;
         77:69:1a:fb:23:59:17:da:65:5c:ab:d2:97:db:a1:68:f6:86:&#xD;
         92:bb:2d:e5:73:e3:96:af:94:21:74:3b:70:79:32:23:37:0a:&#xD;
         5b:84:6c:ea:7c:cb:ef:41:4c:2d:4f:e7:83:4f:f7:da:f7:03:&#xD;
         8d:e0:b8:d0:f6:17:38:78:ee:06:3b:d8:c3:43:98:4f:31:ef:&#xD;
         45:3f:07:7f:d9:e6:9d:d6:01:f4:0a:84:6c:7f:00:82:b5:99:&#xD;
         d6:e4:2a:28:49:0a:cf:ac:5c:1a:87:22:63:f0:32:af:34:17:&#xD;
         3c:c1:eb:96:66:1b:30:af:23:30:86:ea:ea:18:20:dd:e7:f8:&#xD;
         e2:4b:d7:19:d3:e5:be:32:5d:eb:28:96:c2:dd:d0:1b:3f:2a:&#xD;
         54:36:45:6d:49:72:b8:17&#xD;
</ds:X509Certificate>
  </ds:X509Data>
  <ds:KeyValue>
    <ds:RSAKeyValue>
      <ds:Modulus>00:92:93:e4:32:35:7f:17:b1:88:93:28:10:19:51:&#xD;
                    1b:43:24:ec:c0:8d:01:24:6a:76:ff:87:8e:6f:77:&#xD;
                    04:dc:05:2f:15:52:06:6c:77:d2:f6:93:01:6c:2f:&#xD;
                    05:dc:10:cf:75:09:61:55:80:c9:a3:cf:2a:1d:24:&#xD;
                    ac:9b:0a:97:59:a4:37:de:78:f9:7b:02:30:2a:77:&#xD;
                    80:58:fd:58:f3:65:26:e6:4e:32:2e:80:a8:fe:a7:&#xD;
                    91:08:d2:a1:b4:c5:b1:c8:15:1f:4d:de:82:83:9b:&#xD;
                    03:a4:ce:cd:69:b2:40:e0:e3:ff:1b:13:e3:2d:f4:&#xD;
                    9b:26:95:78:d0:c0:1c:02:4a:e0:63:c7:30:1a:fd:&#xD;
                    8d:74:3b:33:6b:d6:e8:46:a6:30:17:0b:6b:45:c5:&#xD;
                    2d:46:ef:9e:00:cf:3c:23:61:0c:f5:e2:18:be:a7:&#xD;
                    a9:25:79:1d:f0:e4:29:61:71:94:54:b8:38:93:a5:&#xD;
                    f1:53:1e:74:37:43:75:67:e4:0c:c3:43:f1:5e:4a:&#xD;
                    4d:23:82:bd:5a:e0:da:4a:fa:6e:76:2d:2c:01:ce:&#xD;
                    86:72:90:a9:87:b3:30:24:cf:ed:b5:4a:7e:7f:5f:&#xD;
                    4e:08:24:14:f5:4f:a6:8f:84:5a:9f:3f:bc:4b:a7:&#xD;
                    97:10:ae:39:8b:98:45:83:d2:d3:64:ef:22:17:71:&#xD;
                    d4:71&#xD;
</ds:Modulus>
      <ds:Exponent>65537</ds:Exponent>
    </ds:RSAKeyValue>
  </ds:KeyValue>
</ds:Keyinfo><ds:Object xmlns:etsi="http://uri.etsi.org/01903/v1.3.2#">
  <etsi:QualifyingProperties xmlns:etsi="http://uri.etsi.org/01903/v1.3.2#" Target="#refQualifyingProperties">
  <etsi:SignedProperties id="Salgraf-PropiedadFirma">
  <etsi:SignedSignatureProperties>
    <etsi:SigningTime xmlns:etsi="http://uri.etsi.org/01903/v1.3.2#">2014-08-29T21:10:34+02:00</etsi:SigningTime>
    <etsi:SigningCertificate>
      <etsi:Cert>
        <etsi:CertDigest>
          <ds:DigestMethod Algorithm="http://www.w3.org/2000/09/xmldsig#sha1"/>
          <ds:DigestValue id="digestSigned">WgIwpCTeMIEAqw5/b8OisIwrQ+I=</ds:DigestValue>
        </etsi:CertDigest>
        <etsi:IssuerSerial>
          <ds:X509SerialNumber>1313023559</ds:X509SerialNumber>
          <ds:X509IssuerName>CN = AC BANCO CENTRAL DEL ECUADOR&#xD;
L = QUITO&#xD;
OU = ENTIDAD DE CERTIFICACION DE INFORMACION-ECIBCE&#xD;
O = BANCO CENTRAL DEL ECUADOR&#xD;
C = EC</ds:X509IssuerName>
        </etsi:IssuerSerial>
      </etsi:Cert>
    </etsi:SigningCertificate>
  </etsi:SignedSignatureProperties>
</etsi:SignedProperties>
</etsi:QualifyingProperties>
</ds:Object></ds:Signature>
